instagramapi/__init__.py
instagramapi/api_helper.py
instagramapi/configuration.py
instagramapi/instagramapi_client.py
instagramapi/controllers/__init__.py
instagramapi/controllers/base_controller.py
instagramapi/controllers/comments_controller.py
instagramapi/controllers/geographies_controller.py
instagramapi/controllers/likes_controller.py
instagramapi/controllers/locations_controller.py
instagramapi/controllers/media_controller.py
instagramapi/controllers/relationships_controller.py
instagramapi/controllers/tags_controller.py
instagramapi/controllers/users_controller.py
instagramapi/exceptions/__init__.py
instagramapi/exceptions/api_exception.py
instagramapi/exceptions/o_auth_provider_exception.py
instagramapi/http/__init__.py
instagramapi/http/http_call_back.py
instagramapi/http/http_method_enum.py
instagramapi/http/http_request.py
instagramapi/http/http_response.py
instagramapi/http/auth/__init__.py
instagramapi/http/auth/api_key.py
instagramapi/http/auth/instagram_auth.py
instagramapi/models/__init__.py
instagramapi/models/action_enum.py
instagramapi/models/caption_data.py
instagramapi/models/comment_entry.py
instagramapi/models/comments_collection.py
instagramapi/models/comments_response.py
instagramapi/models/cursor_pagination_info.py
instagramapi/models/id_pagination_info.py
instagramapi/models/image_info.py
instagramapi/models/images_data.py
instagramapi/models/incoming_status_enum.py
instagramapi/models/likes_collection.py
instagramapi/models/location_info.py
instagramapi/models/location_info_response.py
instagramapi/models/location_search_response.py
instagramapi/models/media_entry.py
instagramapi/models/media_entry_response.py
instagramapi/models/media_list_response.py
instagramapi/models/media_search_response.py
instagramapi/models/meta_data.py
instagramapi/models/o_auth_provider_error_enum.py
instagramapi/models/o_auth_scope_instagram_auth_enum.py
instagramapi/models/o_auth_token.py
instagramapi/models/outgoing_status_enum.py
sdk_instagram-1.0.0.dist-info/licenses/LICENSE
sdk_instagram-1.0.0.dist-info/METADATA
sdk_instagram-1.0.0.dist-info/WHEEL
sdk_instagram-1.0.0.dist-info/top_level.txt
sdk_instagram-1.0.0.dist-info/RECORD
